pytorch_ext/__init__.py
pytorch_ext/model_training/__init__.py
pytorch_ext/model_training/callbacks.py
pytorch_ext/model_training/common.py
pytorch_ext/model_training/model_trainer.py
pytorch_ext/torchvision/__init__.py
pytorch_ext/torchvision/transforms.py
pytorch_ext/visdom_board/__init__.py
pytorch_ext/visdom_board/core.py
pytorch_ext/visdom_board/html_utils.py
pytorch_ext/visdom_board/manager.py
pytorch_ext/visdom_board/misc.py
pytorch_ext/visdom_board/plotting.py
pytorch_ext-0.8.1.dist-info/LICENSE
pytorch_ext-0.8.1.dist-info/METADATA
pytorch_ext-0.8.1.dist-info/WHEEL
pytorch_ext-0.8.1.dist-info/top_level.txt
pytorch_ext-0.8.1.dist-info/RECORD
